[
    {
        "name": "",
        "message": "電書コードは登録されています。",
        "id": 29,
        "name_id": -1
    },
    {
        "name": "",
        "message": "解除しますか？（いつでも再入力出来ます）",
        "id": 45,
        "name_id": -1
    },
    {
        "name": "",
        "message": "解除します",
        "id": 62,
        "type": "select"
    },
    {
        "name": "",
        "message": "いいえ、戻ります",
        "id": 65,
        "type": "select"
    },
    {
        "name": "",
        "message": "コードを解除しました。分岐展開は以前のものに戻ります。",
        "id": 98,
        "name_id": -1
    },
    {
        "name": "",
        "message": "タイトル画面に戻ります。",
        "id": 114,
        "name_id": -1
    },
    {
        "name": "",
        "message": "登録を開始します。お手元の電子書籍「エンキドゥの虚」の巻末を参照下さい。",
        "id": 132,
        "name_id": -1
    },
    {
        "name": "",
        "message": "正しいコードをひとつずつ選択し、入力して下さい。",
        "id": 148,
        "name_id": -1
    },
    {
        "name": "",
        "message": "SEDULITATEM",
        "id": 167,
        "type": "select"
    },
    {
        "name": "",
        "message": "CONTRARIE",
        "id": 170,
        "type": "select"
    },
    {
        "name": "",
        "message": "SACRUM",
        "id": 173,
        "type": "select"
    },
    {
        "name": "",
        "message": "URALIS",
        "id": 213,
        "type": "select"
    },
    {
        "name": "",
        "message": "EPILEPSIAM",
        "id": 216,
        "type": "select"
    },
    {
        "name": "",
        "message": "MULIERCULA",
        "id": 219,
        "type": "select"
    },
    {
        "name": "",
        "message": "VITIOSUS",
        "id": 257,
        "type": "select"
    },
    {
        "name": "",
        "message": "LIGNUM",
        "id": 260,
        "type": "select"
    },
    {
        "name": "",
        "message": "LUCUBRATE",
        "id": 263,
        "type": "select"
    },
    {
        "name": "",
        "message": "SANGUINUM",
        "id": 300,
        "type": "select"
    },
    {
        "name": "",
        "message": "SUBVERTIT",
        "id": 303,
        "type": "select"
    },
    {
        "name": "",
        "message": "BELLUM",
        "id": 306,
        "type": "select"
    },
    {
        "name": "",
        "message": "HOSTIS",
        "id": 343,
        "type": "select"
    },
    {
        "name": "",
        "message": "EVANGELIZARE",
        "id": 346,
        "type": "select"
    },
    {
        "name": "",
        "message": "IMPAVIDE",
        "id": 349,
        "type": "select"
    },
    {
        "name": "",
        "message": "正しい電子書籍コードが入力されました。一部ルートを改変しました。",
        "id": 396,
        "name_id": -1
    },
    {
        "name": "",
        "message": "正しい電子書籍コードではありません。もう一度入力しますか？",
        "id": 414,
        "name_id": -1
    },
    {
        "name": "",
        "message": "はい",
        "id": 430,
        "type": "select"
    },
    {
        "name": "",
        "message": "いいえ",
        "id": 433,
        "type": "select"
    }
]